barmeup_opt/Ingredient.py
barmeup_opt/ModelBuilder.py
barmeup_opt/ModelContainer.py
barmeup_opt/__init__.py
barmeup_opt/.idea/barmeup.iml
barmeup_opt/.idea/misc.xml
barmeup_opt/.idea/modules.xml
barmeup_opt/.idea/vcs.xml
barmeup_opt/.idea/workspace.xml
barmeup_opt/.idea/inspectionProfiles/profiles_settings.xml
barmeup_opt-0.3.dist-info/LICENSE
barmeup_opt-0.3.dist-info/WHEEL
barmeup_opt-0.3.dist-info/METADATA
barmeup_opt-0.3.dist-info/RECORD
