Metadata-Version: 2.1
Name: barmeup_opt
Version: 0.3
Summary: An amazing sample package!
Home-page: https://github.com/RichardOberdieck/BarMeUp_Opt
License: UNKNOWN
Author: Richard Oberdieck, Ruben Menke
Author-email: r.oberdieck@gmail.com
Classifier: License :: OSI Approved :: GNU General Public License v3 or later (GPLv3+)
